fetchers23/__init__.py
fetchers23/get_all_links.py
fetchers23-0.1.0.dist-info/METADATA
fetchers23-0.1.0.dist-info/WHEEL
fetchers23-0.1.0.dist-info/RECORD
