Metadata-Version: 2.1
Name: fetchers23
Version: 0.1.0
Summary: 
Author: Maria Fernanda Gonzalez
Author-email: mariagr@vedur.is
Requires-Python: >=3.10,<4.0
Classifier: Programming Language :: Python :: 3
Classifier: Programming Language :: Python :: 3.10
Classifier: Programming Language :: Python :: 3.11
Requires-Dist: beautifulsoup4 (==4.10)
